LICENSE
lssvr/__init__.py
lssvr/lssvr.py
lssvr-0.1.0.dist-info/LICENSE
lssvr-0.1.0.dist-info/WHEEL
lssvr-0.1.0.dist-info/METADATA
lssvr-0.1.0.dist-info/RECORD
