Metadata-Version: 2.1
Name: lssvr
Version: 0.1.0
Summary: 
Home-page: https://github.com/zealberth/lssvr
License: MIT
Keywords: machine-learning,data-science,lssvr,regression
Author: José Alberth
Author-email: jalberth14@gmail.com
Requires-Python: >=3.8,<4.0
Classifier: License :: OSI Approved :: MIT License
Classifier: Operating System :: OS Independent
Classifier: Programming Language :: Python :: 3
Classifier: Programming Language :: Python :: 3.8
Classifier: Programming Language :: Python :: 3.9
Classifier: Topic :: Software Development :: Libraries :: Python Modules
Requires-Dist: numpy (>=1.19.2,<2.0.0)
Requires-Dist: scikit-learn (>=0.23.2,<0.24.0)
Requires-Dist: scipy (>=1.5.2,<2.0.0)
Project-URL: Repository, https://github.com/zealberth/lssvr
